Metadata-Version: 2.1
Name: pybracket
Version: 1.0.0
Summary: Add brackets and good semicolons to Python
Home-page: https://github.com/donno2048/pybracket
Author: Elisha Hollander
Author-email: just4now666666@gmail.com
License: MIT
Project-URL: Documentation, https://github.com/donno2048/pybracket#readme
Project-URL: Bug Reports, https://github.com/donno2048/pybracket/issues
Project-URL: Source Code, https://github.com/donno2048/pybracket
License-File: LICENSE
